comfyparse/__init__.py
comfyparse/config.py
comfyparse/lexer.py
comfyparse/parser.py
comfyparse-0.0.2.dist-info/LICENSE
comfyparse-0.0.2.dist-info/METADATA
comfyparse-0.0.2.dist-info/WHEEL
comfyparse-0.0.2.dist-info/top_level.txt
comfyparse-0.0.2.dist-info/RECORD
