Metadata-Version: 2.1
Name: comfyparse
Version: 0.0.2
Summary: Configuration definition, parsing, and validation, in the style of argparse.
Home-page: https://github.com/Elemnir/comfyparse
Author: Adam Howard
Author-email: ahoward0920@gmail.com
License: UNKNOWN
Platform: UNKNOWN
License-File: LICENSE
